metamorproxies/__init__.py
metamorproxies/soldier/__init__.py
metamorproxies/soldier/print.py
metamorproxies-0.3.10.6.dist-info/METADATA
metamorproxies-0.3.10.6.dist-info/WHEEL
metamorproxies-0.3.10.6.dist-info/top_level.txt
metamorproxies-0.3.10.6.dist-info/RECORD
