Metadata-Version: 2.4
Name: metamorproxies
Version: 0.3.10.6
Summary: Library for working wih proxies
Home-page: https://github.com/reinanbr/metamorproxies
Author: Reinan Br
Author-email: slimchatuba@gmail.com
License: MIT License
Keywords: proxies
Requires-Dist: attrs
Requires-Dist: certifi
Requires-Dist: charset-normalizer
Requires-Dist: colorama
Requires-Dist: h11
Requires-Dist: idna
Requires-Dist: iniconfig
Requires-Dist: kitano
Requires-Dist: outcome
Requires-Dist: packaging
Requires-Dist: pluggy
Requires-Dist: Pygments
Requires-Dist: PySocks
Requires-Dist: pytest
Requires-Dist: python-dotenv
Requires-Dist: requests
Requires-Dist: selenium
Requires-Dist: setuptools
Requires-Dist: sniffio
Requires-Dist: sortedcontainers
Requires-Dist: trio
Requires-Dist: trio-websocket
Requires-Dist: typing_extensions
Requires-Dist: urllib3
Requires-Dist: webdriver-manager
Requires-Dist: websocket-client
Requires-Dist: wsproto
Dynamic: author
Dynamic: author-email
Dynamic: description
Dynamic: description-content-type
Dynamic: home-page
Dynamic: keywords
Dynamic: license
Dynamic: requires-dist
Dynamic: summary
